SuperKiro/__init__.py
SuperKiro/__main__.py
setup/__init__.py
setup/cli/__init__.py
setup/cli/base.py
setup/cli/commands/__init__.py
setup/cli/commands/backup.py
setup/cli/commands/install.py
setup/cli/commands/kiro_init.py
setup/cli/commands/uninstall.py
setup/cli/commands/update.py
setup/components/__init__.py
setup/components/agents.py
setup/components/commands.py
setup/components/core.py
setup/components/mcp.py
setup/components/mcp_docs.py
setup/components/modes.py
setup/core/__init__.py
setup/core/base.py
setup/core/installer.py
setup/core/registry.py
setup/core/validator.py
setup/data/__init__.py
setup/data/features.json
setup/data/requirements.json
setup/services/__init__.py
setup/services/claude_md.py
setup/services/config.py
setup/services/files.py
setup/services/settings.py
setup/templates/__init__.py
setup/templates/kiro/__init__.py
setup/templates/kiro/steering/__init__.py
setup/templates/kiro/steering/sk_backend_architect.md
setup/templates/kiro/steering/sk_devops_architect.md
setup/templates/kiro/steering/sk_frontend_architect.md
setup/templates/kiro/steering/sk_learning_guide.md
setup/templates/kiro/steering/sk_performance_engineer.md
setup/templates/kiro/steering/sk_python_expert.md
setup/templates/kiro/steering/sk_quality_engineer.md
setup/templates/kiro/steering/sk_refactoring_expert.md
setup/templates/kiro/steering/sk_requirements_analyst.md
setup/templates/kiro/steering/sk_root_cause_analyst.md
setup/templates/kiro/steering/sk_security_engineer.md
setup/templates/kiro/steering/sk_socratic_mentor.md
setup/templates/kiro/steering/sk_system_architect.md
setup/templates/kiro/steering/sk_technical_writer.md
setup/templates/kiro/steering/super_kiro.md
setup/templates/kiro/steering/commands/sk_analyze.md
setup/templates/kiro/steering/commands/sk_brainstorm.md
setup/templates/kiro/steering/commands/sk_build.md
setup/templates/kiro/steering/commands/sk_business_panel.md
setup/templates/kiro/steering/commands/sk_cleanup.md
superkiro-0.1.0.dist-info/licenses/LICENSE
superkiro-0.1.0.dist-info/METADATA
superkiro-0.1.0.dist-info/WHEEL
superkiro-0.1.0.dist-info/entry_points.txt
superkiro-0.1.0.dist-info/top_level.txt
superkiro-0.1.0.dist-info/RECORD
