Metadata-Version: 2.4
Name: SuperKiro
Version: 0.1.0
Summary: SuperKiro Framework Management Hub - AI-enhanced development framework for Kiro-compatible workflows
Author-email: NomenAK <anton.knoery@gmail.com>, Mithun Gowda B <mithungowda.b7411@gmail.com>
License: MIT
Project-URL: Homepage, https://github.com/SuperClaude-Org/SuperKiro_Framework
Project-URL: GitHub, https://github.com/SuperClaude-Org/SuperKiro_Framework
Project-URL: Bug Tracker, https://github.com/SuperClaude-Org/SuperKiro_Framework/issues
Project-URL: Mithun Gowda B, https://github.com/mithun50
Project-URL: NomenAK, https://github.com/NomenAK
Keywords: claude,ai,automation,framework,mcp,agents,development,code-generation,assistant
Classifier: Development Status :: 4 - Beta
Classifier: Intended Audience :: Developers
Classifier: Operating System :: OS Independent
Classifier: Programming Language :: Python :: 3
Classifier: Programming Language :: Python :: 3.8
Classifier: Programming Language :: Python :: 3.9
Classifier: Programming Language :: Python :: 3.10
Classifier: Programming Language :: Python :: 3.11
Classifier: Programming Language :: Python :: 3.12
Classifier: Topic :: Software Development :: Libraries :: Python Modules
Classifier: Topic :: Software Development :: Code Generators
Classifier: Topic :: Scientific/Engineering :: Artificial Intelligence
Classifier: Environment :: Console
Requires-Python: >=3.8
License-File: LICENSE
Requires-Dist: setuptools>=45.0.0
Requires-Dist: importlib-metadata>=1.0.0; python_version < "3.8"
Provides-Extra: dev
Requires-Dist: pytest>=6.0; extra == "dev"
Requires-Dist: pytest-cov>=2.0; extra == "dev"
Requires-Dist: black>=22.0; extra == "dev"
Requires-Dist: flake8>=4.0; extra == "dev"
Requires-Dist: mypy>=0.900; extra == "dev"
Provides-Extra: test
Requires-Dist: pytest>=6.0; extra == "test"
Requires-Dist: pytest-cov>=2.0; extra == "test"
Dynamic: license-file
